<?xml version="1.0" encoding="UTF-8"?>
<!DOCTYPE plist PUBLIC "-//Apple//DTD PLIST 1.0//EN" "http://www.apple.com/DTDs/PropertyList-1.0.dtd">
<plist version="1.0">
<dict>
	<key>AssetType</key>
	<string>com.apple.MobileAsset.Trial.Siri.SiriTextToSpeech</string>
	<key>Assets</key>
	<array>
		<dict>
			<key>ArchiveDecryptionKey</key>
			<string>HyTzc522LJc1EgPZG481RpbiteSOZbjCVW6iNw5z4qI=</string>
			<key>ArchiveID</key>
			<string>A6+OkAADGt+mSjJyP7do71mb4OXYrouFaAkbf32/tnI=</string>
			<key>AssetFormat</key>
			<string>AppleArchive</string>
			<key>AssetSpecifier</key>
			<string>com.apple.siri.tts.voice.en_US.nora.neural.premium-en_US-iPhone</string>
			<key>AssetType</key>
			<string>com.apple.MobileAsset.Trial.Siri.SiriTextToSpeech</string>
			<key>AssetVersion</key>
			<string>1899.0.0.13.100140,0</string>
			<key>AssetVersionInfo</key>
			<dict>
				<key>AssetVersionGroup</key>
				<integer>0</integer>
				<key>AssetVersionLong</key>
				<string>1899.0.0.13.100140,0</string>
				<key>AssetVersionTuple</key>
				<string>1899.0.0.13.100140</string>
				<key>BuildVersionTuple</key>
				<string>13.13.100140</string>
				<key>BundleVersionTuple</key>
				<string>1899.0.0</string>
			</dict>
			<key>Build</key>
			<string>13M100140</string>
			<key>Factor</key>
			<string>com.apple.siri.tts.voice.en_US.nora.neural.premium</string>
			<key>Ramp</key>
			<false/>
			<key>_CompressionAlgorithm</key>
			<string>AppleArchive</string>
			<key>_DownloadSize</key>
			<integer>83886080</integer>
			<key>_IsMAAutoAsset</key>
			<true/>
			<key>_Measurement</key>
			<data>
			rATV9iysbGmVr0qjQa2hNshtNv0=
			</data>
			<key>_MeasurementAlgorithm</key>
			<string>SHA-1</string>
			<key>_OSVersionCompatibilities</key>
			<dict>
				<key>Apple TV</key>
				<dict>
					<key>_MinOSVersion</key>
					<string>18.0</string>
				</dict>
				<key>Apple Vision</key>
				<dict>
					<key>_MinOSVersion</key>
					<string>2.0</string>
				</dict>
				<key>Apple Watch</key>
				<dict>
					<key>_MinOSVersion</key>
					<string>11.0</string>
				</dict>
				<key>HomePod</key>
				<dict>
					<key>_MinOSVersion</key>
					<string>18.0</string>
				</dict>
				<key>Mac</key>
				<dict>
					<key>_MinOSVersion</key>
					<string>15.0</string>
				</dict>
				<key>iPad</key>
				<dict>
					<key>_MinOSVersion</key>
					<string>18.0</string>
				</dict>
				<key>iPad Simulator</key>
				<dict>
					<key>_MinOSVersion</key>
					<string>18.0</string>
				</dict>
				<key>iPhone</key>
				<dict>
					<key>_MinOSVersion</key>
					<string>18.0</string>
				</dict>
				<key>iPhone Simulator</key>
				<dict>
					<key>_MinOSVersion</key>
					<string>18.0</string>
				</dict>
				<key>rProd Device</key>
				<dict>
					<key>_MinOSVersion</key>
					<string>2.0</string>
				</dict>
			</dict>
			<key>_PreSoftwareUpdateAssetStaging</key>
			<true/>
			<key>_UnarchivedSize</key>
			<integer>105291776</integer>
			<key>__BaseURL</key>
			<string>https://updates.cdn-apple.com/2024/Trial/mobileassets/023-02176/F218AE79-B6B8-4457-8ABB-08F444676783/</string>
			<key>__CanUseLocalCacheServer</key>
			<true/>
			<key>__RelativePath</key>
			<string>com_apple_MobileAsset_Trial_Siri_SiriTextToSpeech/D6C7F965-924A-4F20-B1DD-1DBC13F0BA07.aar</string>
			<key>assetSize</key>
			<string>83688889</string>
			<key>gender</key>
			<string>female</string>
			<key>ttsCompatibilityVersion</key>
			<string>68</string>
			<key>ttsContentVersion</key>
			<string>1899</string>
			<key>version</key>
			<string>1899.0.0</string>
		</dict>
	</array>
	<key>CachedAssetSetId</key>
	<string>34dc3d06-d47e-4e7a-a60e-77b8695146c3</string>
	<key>DownloadedFromLive</key>
	<string>https://gdmf.apple.com/v2/assets</string>
	<key>catalogInfo</key>
	<dict>
		<key>isLiveServer</key>
		<true/>
	</dict>
	<key>lastTimeChecked</key>
	<date>2024-07-19T03:05:50Z</date>
	<key>postedDate</key>
	<date>2024-07-18T00:00:00Z</date>
</dict>
</plist>
